bjontegaard/__init__.py
bjontegaard/bjontegaard_delta.py
bjontegaard/evaluate.py
bjontegaard/functions.py
bjontegaard/interpolation.py
bjontegaard-1.3.0.dist-info/LICENSE
bjontegaard-1.3.0.dist-info/METADATA
bjontegaard-1.3.0.dist-info/WHEEL
bjontegaard-1.3.0.dist-info/top_level.txt
bjontegaard-1.3.0.dist-info/RECORD
