Metadata-Version: 2.1
Name: bjontegaard
Version: 1.3.0
Summary: Calculate the Bjonteegard-Delta metric with different interpolation methods
Home-page: https://github.com/FAU-LMS/bjontegaard
Author: bjontegaard contributors
Author-email: christian.herglotz@fau.de
Project-URL: Bug Tracker, https://github.com/FAU-LMS/bjontegaard/issues
Classifier: Programming Language :: Python :: 3
Classifier: Programming Language :: Python :: 3.6
Classifier: Programming Language :: Python :: 3.7
Classifier: Programming Language :: Python :: 3.8
Classifier: Programming Language :: Python :: 3.9
Classifier: Programming Language :: Python :: 3.10
Classifier: License :: OSI Approved :: BSD License
Classifier: Operating System :: OS Independent
Classifier: Intended Audience :: Science/Research
Classifier: Intended Audience :: Education
Classifier: Intended Audience :: Developers
Requires-Python: >=3.6
License-File: LICENSE
Requires-Dist: numpy
Requires-Dist: scipy
Requires-Dist: matplotlib
